uestcnet/__init__.py
uestcnet/uestc_net.py
uestcnet/util/__init__.py
uestcnet/util/ct_base64.py
uestcnet/util/hmd5.py
uestcnet/util/xEncode.py
uestcnet-0.4.dist-info/LICENSE
uestcnet-0.4.dist-info/METADATA
uestcnet-0.4.dist-info/WHEEL
uestcnet-0.4.dist-info/top_level.txt
uestcnet-0.4.dist-info/RECORD
