Metadata-Version: 2.1
Name: uestcnet
Version: 0.4
Author: atfwus
Author-email: atfwus@qq.com
License-File: LICENSE
Requires-Dist: Requests ==2.31.0
